meru_app/__init__.py
meru_app/meru_app.py
meru_app-1.0.2.dist-info/METADATA
meru_app-1.0.2.dist-info/WHEEL
meru_app-1.0.2.dist-info/top_level.txt
meru_app-1.0.2.dist-info/RECORD
