Metadata-Version: 2.1
Name: meru-app
Version: 1.0.2
Summary: Meru Python API
Home-page: UNKNOWN
License: UNKNOWN
Platform: UNKNOWN
